{"kind":"FileIndex","apiVersion":"v1","Files":{".classpath":{"Size":1378,"LastModifiedDate":"2019-11-17T16:52:14.795694131-07:00"},".gitignore":{"Size":218,"LastModifiedDate":"2019-11-17T16:49:12.080432632-07:00"},".project":{"Size":1640,"LastModifiedDate":"2019-11-17T16:52:32.820216318-07:00"},".settings":{"Size":4096,"LastModifiedDate":"2019-11-17T16:52:32.83621679-07:00"},".settings/.jsdtscope":{"Size":626,"LastModifiedDate":"2019-11-17T16:52:32.832216672-07:00"},".settings/org.eclipse.core.resources.prefs":{"Size":150,"LastModifiedDate":"2019-11-17T16:52:11.859611062-07:00"},".settings/org.eclipse.jdt.core.prefs":{"Size":605,"LastModifiedDate":"2019-11-17T16:52:12.143619071-07:00"},".settings/org.eclipse.jpt.core.prefs":{"Size":126,"LastModifiedDate":"2019-11-17T16:52:32.984221157-07:00"},".settings/org.eclipse.m2e.core.prefs":{"Size":86,"LastModifiedDate":"2019-11-17T16:52:10.671577622-07:00"},".settings/org.eclipse.wst.common.component":{"Size":724,"LastModifiedDate":"2019-11-17T16:52:12.391626074-07:00"},".settings/org.eclipse.wst.common.project.facet.core.prefs.xml":{"Size":454,"LastModifiedDate":"2019-11-17T16:52:32.784215255-07:00"},".settings/org.eclipse.wst.common.project.facet.core.xml":{"Size":473,"LastModifiedDate":"2019-11-17T16:52:42.652509372-07:00"},".settings/org.eclipse.wst.jsdt.ui.superType.container":{"Size":49,"LastModifiedDate":"2019-11-17T16:52:32.832216672-07:00"},".settings/org.eclipse.wst.jsdt.ui.superType.name":{"Size":6,"LastModifiedDate":"2019-11-17T16:52:32.832216672-07:00"},".settings/org.eclipse.wst.validation.prefs":{"Size":48,"LastModifiedDate":"2019-11-17T16:52:12.403626413-07:00"},".sts4-cache":{"Size":4096,"LastModifiedDate":"2019-11-20T12:20:11.094043755-07:00"},".sts4-cache/classpath-data.json":{"Size":19081,"LastModifiedDate":"2019-11-20T15:39:09.469242164-07:00"},".tern-project":{"Size":149,"LastModifiedDate":"2019-11-18T15:50:16.199031058-07:00"},"Dockerfile":{"Size":90,"LastModifiedDate":"2019-11-17T16:49:12.084432637-07:00"},"buildAndRun.bat":{"Size":297,"LastModifiedDate":"2019-11-17T16:49:12.080432632-07:00"},"buildAndRun.sh":{"Size":291,"LastModifiedDate":"2019-11-17T16:49:12.084432637-07:00"},"pom.xml":{"Size":3126,"LastModifiedDate":"2019-11-20T15:39:09.201237651-07:00"},"src":{"Size":4096,"LastModifiedDate":"2019-11-17T16:49:12.072432624-07:00"},"src/main":{"Size":4096,"LastModifiedDate":"2019-11-17T16:49:12.072432624-07:00"},"src/main/java":{"Size":4096,"LastModifiedDate":"2019-11-18T14:20:29.958448112-07:00"},"src/main/java/ca":{"Size":4096,"LastModifiedDate":"2019-11-18T14:20:29.838445098-07:00"},"src/main/java/ca/assignment04":{"Size":4096,"LastModifiedDate":"2019-11-20T15:23:06.324663159-07:00"},"src/main/java/ca/assignment04/config":{"Size":4096,"LastModifiedDate":"2019-11-18T14:31:12.412164936-07:00"},"src/main/java/ca/assignment04/config/ApplicationConfig.java":{"Size":1343,"LastModifiedDate":"2019-11-20T16:03:32.455874638-07:00"},"src/main/java/ca/assignment04/entities":{"Size":4096,"LastModifiedDate":"2019-11-18T14:10:49.366907424-07:00"},"src/main/java/ca/assignment04/entities/CalendarEvent.java":{"Size":1581,"LastModifiedDate":"2019-11-20T18:41:14.721878514-07:00"},"src/main/java/ca/assignment04/mail":{"Size":4096,"LastModifiedDate":"2019-11-21T17:42:36.180437803-07:00"},"src/main/java/ca/assignment04/mail/Decryptor.java":{"Size":334,"LastModifiedDate":"2019-11-20T15:26:35.912078717-07:00"},"src/main/java/ca/assignment04/mail/SendMail.java":{"Size":2010,"LastModifiedDate":"2019-11-20T20:34:47.435911776-07:00"},"src/main/java/ca/assignment04/service":{"Size":4096,"LastModifiedDate":"2019-11-21T19:16:54.242781771-07:00"},"src/main/java/ca/assignment04/service/CalendarEventService.java":{"Size":4518,"LastModifiedDate":"2019-11-21T19:13:18.737992815-07:00"},"src/main/java/ca/assignment04/service/EventInterceptor.java":{"Size":1343,"LastModifiedDate":"2019-11-21T19:11:45.330767467-07:00"},"src/main/java/ca/assignment04/service/LoggerProducer.java":{"Size":358,"LastModifiedDate":"2019-11-21T19:17:13.843069454-07:00"},"src/main/java/ca/assignment04/service/SecurityRole.java":{"Size":77,"LastModifiedDate":"2019-11-21T18:39:38.205324237-07:00"},"src/main/java/ca/assignment04/web":{"Size":4096,"LastModifiedDate":"2019-11-18T15:25:02.254988435-07:00"},"src/main/java/ca/assignment04/web/CalendarEventController.java":{"Size":3644,"LastModifiedDate":"2019-11-21T19:00:05.988296265-07:00"},"src/main/resources":{"Size":4096,"LastModifiedDate":"2019-11-17T16:49:12.072432624-07:00"},"src/main/resources/META-INF":{"Size":4096,"LastModifiedDate":"2019-11-17T16:49:12.072432624-07:00"},"src/main/resources/META-INF/microprofile-config.properties":{"Size":38,"LastModifiedDate":"2019-11-17T16:49:12.072432624-07:00"},"src/main/resources/META-INF/persistence.xml":{"Size":868,"LastModifiedDate":"2019-11-21T17:48:03.337309041-07:00"},"src/main/webapp":{"Size":4096,"LastModifiedDate":"2019-11-19T18:09:04.206051846-07:00"},"src/main/webapp/CreateEvent.xhtml":{"Size":1336,"LastModifiedDate":"2019-11-19T11:49:30.57558202-07:00"},"src/main/webapp/EditEvent.xhtml":{"Size":1982,"LastModifiedDate":"2019-11-21T19:22:06.449277466-07:00"},"src/main/webapp/ListEvent.xhtml":{"Size":1887,"LastModifiedDate":"2019-11-20T17:39:29.91662462-07:00"},"src/main/webapp/WEB-INF":{"Size":4096,"LastModifiedDate":"2019-11-20T15:51:20.607089786-07:00"},"src/main/webapp/WEB-INF/beans.xml":{"Size":286,"LastModifiedDate":"2019-11-17T16:49:12.080432632-07:00"},"src/main/webapp/WEB-INF/jboss-web.xml":{"Size":109,"LastModifiedDate":"2019-11-20T15:51:54.444044992-07:00"},"src/main/webapp/WEB-INF/payara-web.xml":{"Size":260,"LastModifiedDate":"2019-11-17T16:49:12.080432632-07:00"},"src/main/webapp/WEB-INF/templates":{"Size":4096,"LastModifiedDate":"2019-11-18T15:45:59.12377112-07:00"},"src/main/webapp/WEB-INF/templates/template.xhtml":{"Size":3934,"LastModifiedDate":"2019-11-20T15:03:16.865279116-07:00"},"src/main/webapp/WEB-INF/web.xml":{"Size":2618,"LastModifiedDate":"2019-11-21T19:06:13.957079845-07:00"},"src/main/webapp/eventDetail.xhtml":{"Size":2734,"LastModifiedDate":"2019-11-21T17:42:57.185264189-07:00"},"src/main/webapp/index.xhtml":{"Size":2820,"LastModifiedDate":"2019-11-21T19:41:58.737023221-07:00"},"src/test":{"Size":4096,"LastModifiedDate":"2019-11-17T16:49:12.072432624-07:00"},"src/test/java":{"Size":4096,"LastModifiedDate":"2019-11-17T16:49:12.072432624-07:00"},"target":{"Size":4096,"LastModifiedDate":"2019-11-21T19:42:44.274166111-07:00"},"target/classes":{"Size":4096,"LastModifiedDate":"2019-11-21T19:42:43.506082823-07:00"},"target/classes/META-INF":{"Size":4096,"LastModifiedDate":"2019-11-21T19:42:41.829900683-07:00"},"target/classes/META-INF/microprofile-config.properties":{"Size":38,"LastModifiedDate":"2019-11-21T19:42:41.829900683-07:00"},"target/classes/META-INF/persistence.xml":{"Size":868,"LastModifiedDate":"2019-11-21T19:42:41.829900683-07:00"},"target/classes/ca":{"Size":4096,"LastModifiedDate":"2019-11-21T19:42:43.506082823-07:00"},"target/classes/ca/assignment04":{"Size":4096,"LastModifiedDate":"2019-11-21T19:42:43.718105828-07:00"},"target/classes/ca/assignment04/config":{"Size":4096,"LastModifiedDate":"2019-11-21T19:42:43.674101053-07:00"},"target/classes/ca/assignment04/config/ApplicationConfig.class":{"Size":1200,"LastModifiedDate":"2019-11-21T19:42:43.674101053-07:00"},"target/classes/ca/assignment04/entities":{"Size":4096,"LastModifiedDate":"2019-11-21T19:42:43.67010062-07:00"},"target/classes/ca/assignment04/entities/CalendarEvent.class":{"Size":6040,"LastModifiedDate":"2019-11-21T19:42:43.674101053-07:00"},"target/classes/ca/assignment04/mail":{"Size":4096,"LastModifiedDate":"2019-11-21T19:42:43.746108868-07:00"},"target/classes/ca/assignment04/mail/Decryptor.class":{"Size":666,"LastModifiedDate":"2019-11-21T19:42:43.510083257-07:00"},"target/classes/ca/assignment04/mail/SendMail$1.class":{"Size":856,"LastModifiedDate":"2019-11-21T19:42:43.742108433-07:00"},"target/classes/ca/assignment04/mail/SendMail.class":{"Size":4786,"LastModifiedDate":"2019-11-21T19:42:43.750109301-07:00"},"target/classes/ca/assignment04/service":{"Size":4096,"LastModifiedDate":"2019-11-21T19:42:43.706104527-07:00"},"target/classes/ca/assignment04/service/CalendarEventService.class":{"Size":5347,"LastModifiedDate":"2019-11-21T19:42:43.630096279-07:00"},"target/classes/ca/assignment04/service/EventInterceptor.class":{"Size":2325,"LastModifiedDate":"2019-11-21T19:42:43.706104527-07:00"},"target/classes/ca/assignment04/service/LoggerProducer.class":{"Size":979,"LastModifiedDate":"2019-11-21T19:42:43.686102356-07:00"},"target/classes/ca/assignment04/service/SecurityRole.class":{"Size":1031,"LastModifiedDate":"2019-11-21T19:42:43.682101922-07:00"},"target/classes/ca/assignment04/web":{"Size":4096,"LastModifiedDate":"2019-11-21T19:42:43.718105828-07:00"},"target/classes/ca/assignment04/web/CalendarEventController.class":{"Size":5146,"LastModifiedDate":"2019-11-21T19:42:43.722106263-07:00"},"target/dmit2015-assignment04-nmorrish1":{"Size":4096,"LastModifiedDate":"2019-11-21T19:42:44.186-07:00"},"target/dmit2015-assignment04-nmorrish1.war":{"Size":10744387,"LastModifiedDate":"2019-11-21T19:42:44.622203807-07:00"},"target/dmit2015-assignment04-nmorrish1/CreateEvent.xhtml":{"Size":1336,"LastModifiedDate":"2019-11-19T11:49:30.575-07:00"},"target/dmit2015-assignment04-nmorrish1/EditEvent.xhtml":{"Size":1982,"LastModifiedDate":"2019-11-21T19:22:06.449-07:00"},"target/dmit2015-assignment04-nmorrish1/ListEvent.xhtml":{"Size":1887,"LastModifiedDate":"2019-11-20T17:39:29.916-07:00"},"target/dmit2015-assignment04-nmorrish1/META-INF":{"Size":4096,"LastModifiedDate":"2019-11-21T19:42:44.166-07:00"},"target/dmit2015-assignment04-nmorrish1/WEB-INF":{"Size":4096,"LastModifiedDate":"2019-11-21T19:42:44.202-07:00"},"target/dmit2015-assignment04-nmorrish1/WEB-INF/beans.xml":{"Size":286,"LastModifiedDate":"2019-11-17T16:49:12.08-07:00"},"target/dmit2015-assignment04-nmorrish1/WEB-INF/classes":{"Size":4096,"LastModifiedDate":"2019-11-21T19:42:44.19-07:00"},"target/dmit2015-assignment04-nmorrish1/WEB-INF/classes/META-INF":{"Size":4096,"LastModifiedDate":"2019-11-21T19:42:44.19-07:00"},"target/dmit2015-assignment04-nmorrish1/WEB-INF/classes/META-INF/microprofile-config.properties":{"Size":38,"LastModifiedDate":"2019-11-21T19:42:41.829-07:00"},"target/dmit2015-assignment04-nmorrish1/WEB-INF/classes/META-INF/persistence.xml":{"Size":868,"LastModifiedDate":"2019-11-21T19:42:41.829-07:00"},"target/dmit2015-assignment04-nmorrish1/WEB-INF/classes/ca":{"Size":4096,"LastModifiedDate":"2019-11-21T19:42:44.19-07:00"},"target/dmit2015-assignment04-nmorrish1/WEB-INF/classes/ca/assignment04":{"Size":4096,"LastModifiedDate":"2019-11-21T19:42:44.19-07:00"},"target/dmit2015-assignment04-nmorrish1/WEB-INF/classes/ca/assignment04/config":{"Size":4096,"LastModifiedDate":"2019-11-21T19:42:44.19-07:00"},"target/dmit2015-assignment04-nmorrish1/WEB-INF/classes/ca/assignment04/config/ApplicationConfig.class":{"Size":1200,"LastModifiedDate":"2019-11-21T19:42:43.674-07:00"},"target/dmit2015-assignment04-nmorrish1/WEB-INF/classes/ca/assignment04/entities":{"Size":4096,"LastModifiedDate":"2019-11-21T19:42:44.19-07:00"},"target/dmit2015-assignment04-nmorrish1/WEB-INF/classes/ca/assignment04/entities/CalendarEvent.class":{"Size":6040,"LastModifiedDate":"2019-11-21T19:42:43.674-07:00"},"target/dmit2015-assignment04-nmorrish1/WEB-INF/classes/ca/assignment04/mail":{"Size":4096,"LastModifiedDate":"2019-11-21T19:42:44.19-07:00"},"target/dmit2015-assignment04-nmorrish1/WEB-INF/classes/ca/assignment04/mail/Decryptor.class":{"Size":666,"LastModifiedDate":"2019-11-21T19:42:43.51-07:00"},"target/dmit2015-assignment04-nmorrish1/WEB-INF/classes/ca/assignment04/mail/SendMail$1.class":{"Size":856,"LastModifiedDate":"2019-11-21T19:42:43.742-07:00"},"target/dmit2015-assignment04-nmorrish1/WEB-INF/classes/ca/assignment04/mail/SendMail.class":{"Size":4786,"LastModifiedDate":"2019-11-21T19:42:43.75-07:00"},"target/dmit2015-assignment04-nmorrish1/WEB-INF/classes/ca/assignment04/service":{"Size":4096,"LastModifiedDate":"2019-11-21T19:42:44.19-07:00"},"target/dmit2015-assignment04-nmorrish1/WEB-INF/classes/ca/assignment04/service/CalendarEventService.class":{"Size":5347,"LastModifiedDate":"2019-11-21T19:42:43.63-07:00"},"target/dmit2015-assignment04-nmorrish1/WEB-INF/classes/ca/assignment04/service/EventInterceptor.class":{"Size":2325,"LastModifiedDate":"2019-11-21T19:42:43.706-07:00"},"target/dmit2015-assignment04-nmorrish1/WEB-INF/classes/ca/assignment04/service/LoggerProducer.class":{"Size":979,"LastModifiedDate":"2019-11-21T19:42:43.686-07:00"},"target/dmit2015-assignment04-nmorrish1/WEB-INF/classes/ca/assignment04/service/SecurityRole.class":{"Size":1031,"LastModifiedDate":"2019-11-21T19:42:43.682-07:00"},"target/dmit2015-assignment04-nmorrish1/WEB-INF/classes/ca/assignment04/web":{"Size":4096,"LastModifiedDate":"2019-11-21T19:42:44.19-07:00"},"target/dmit2015-assignment04-nmorrish1/WEB-INF/classes/ca/assignment04/web/CalendarEventController.class":{"Size":5146,"LastModifiedDate":"2019-11-21T19:42:43.722-07:00"},"target/dmit2015-assignment04-nmorrish1/WEB-INF/jboss-web.xml":{"Size":109,"LastModifiedDate":"2019-11-20T15:51:54.444-07:00"},"target/dmit2015-assignment04-nmorrish1/WEB-INF/lib":{"Size":4096,"LastModifiedDate":"2019-11-21T19:42:44.226-07:00"},"target/dmit2015-assignment04-nmorrish1/WEB-INF/lib/all-themes-1.0.10.jar":{"Size":1366791,"LastModifiedDate":"2019-09-05T16:33:24.144-06:00"},"target/dmit2015-assignment04-nmorrish1/WEB-INF/lib/bootsfaces-1.4.2.jar":{"Size":2146814,"LastModifiedDate":"2019-10-19T22:46:11.545-06:00"},"target/dmit2015-assignment04-nmorrish1/WEB-INF/lib/commons-lang3-3.9.jar":{"Size":503880,"LastModifiedDate":"2019-11-14T10:10:27.337-07:00"},"target/dmit2015-assignment04-nmorrish1/WEB-INF/lib/h2-1.4.200.jar":{"Size":2303679,"LastModifiedDate":"2019-10-28T14:05:31.375-06:00"},"target/dmit2015-assignment04-nmorrish1/WEB-INF/lib/jakarta.security.enterprise-1.0.1.jar":{"Size":141629,"LastModifiedDate":"2019-11-20T15:38:50.04-07:00"},"target/dmit2015-assignment04-nmorrish1/WEB-INF/lib/jakarta.security.enterprise-api-1.0.1.jar":{"Size":44658,"LastModifiedDate":"2019-11-20T15:38:50.008-07:00"},"target/dmit2015-assignment04-nmorrish1/WEB-INF/lib/jasypt-1.9.3.jar":{"Size":142255,"LastModifiedDate":"2019-09-16T15:47:49.979-06:00"},"target/dmit2015-assignment04-nmorrish1/WEB-INF/lib/omnifaces-3.2.jar":{"Size":729866,"LastModifiedDate":"2019-09-05T16:33:36.297-06:00"},"target/dmit2015-assignment04-nmorrish1/WEB-INF/lib/primefaces-6.2.jar":{"Size":4271042,"LastModifiedDate":"2019-09-05T16:33:38.385-06:00"},"target/dmit2015-assignment04-nmorrish1/WEB-INF/payara-web.xml":{"Size":260,"LastModifiedDate":"2019-11-17T16:49:12.08-07:00"},"target/dmit2015-assignment04-nmorrish1/WEB-INF/templates":{"Size":4096,"LastModifiedDate":"2019-11-21T19:42:44.186-07:00"},"target/dmit2015-assignment04-nmorrish1/WEB-INF/templates/template.xhtml":{"Size":3934,"LastModifiedDate":"2019-11-20T15:03:16.865-07:00"},"target/dmit2015-assignment04-nmorrish1/WEB-INF/web.xml":{"Size":2618,"LastModifiedDate":"2019-11-21T19:06:13.957-07:00"},"target/dmit2015-assignment04-nmorrish1/eventDetail.xhtml":{"Size":2734,"LastModifiedDate":"2019-11-21T17:42:57.185-07:00"},"target/dmit2015-assignment04-nmorrish1/index.xhtml":{"Size":2820,"LastModifiedDate":"2019-11-21T19:41:58.737-07:00"},"target/generated-sources":{"Size":4096,"LastModifiedDate":"2019-11-21T19:42:42.025922025-07:00"},"target/generated-sources/annotations":{"Size":4096,"LastModifiedDate":"2019-11-21T19:42:42.025922025-07:00"},"target/maven-archiver":{"Size":4096,"LastModifiedDate":"2019-11-21T19:42:44.238162212-07:00"},"target/maven-archiver/pom.properties":{"Size":142,"LastModifiedDate":"2019-11-21T19:42:44.246163079-07:00"},"target/maven-status":{"Size":4096,"LastModifiedDate":"2019-11-21T19:42:42.017921155-07:00"},"target/maven-status/maven-compiler-plugin":{"Size":4096,"LastModifiedDate":"2019-11-21T19:42:43.766111037-07:00"},"target/maven-status/maven-compiler-plugin/compile":{"Size":4096,"LastModifiedDate":"2019-11-21T19:42:42.017921155-07:00"},"target/maven-status/maven-compiler-plugin/compile/default-compile":{"Size":4096,"LastModifiedDate":"2019-11-21T19:42:43.754109735-07:00"},"target/maven-status/maven-compiler-plugin/compile/default-compile/createdFiles.lst":{"Size":439,"LastModifiedDate":"2019-11-21T19:42:43.754109735-07:00"},"target/maven-status/maven-compiler-plugin/compile/default-compile/inputFiles.lst":{"Size":1220,"LastModifiedDate":"2019-11-21T19:42:43.754109735-07:00"},"target/maven-status/maven-compiler-plugin/testCompile":{"Size":4096,"LastModifiedDate":"2019-11-21T19:42:43.766111037-07:00"},"target/maven-status/maven-compiler-plugin/testCompile/default-testCompile":{"Size":4096,"LastModifiedDate":"2019-11-21T19:42:43.766111037-07:00"},"target/maven-status/maven-compiler-plugin/testCompile/default-testCompile/inputFiles.lst":{"Size":0,"LastModifiedDate":"2019-11-21T19:42:43.766111037-07:00"}}}